WinPET-1.0.2.dist-info/DESCRIPTION.rst
WinPET-1.0.2.dist-info/METADATA
WinPET-1.0.2.dist-info/RECORD
WinPET-1.0.2.dist-info/WHEEL
WinPET-1.0.2.dist-info/entry_points.txt
WinPET-1.0.2.dist-info/metadata.json
WinPET-1.0.2.dist-info/top_level.txt
winpet/__init__.py
