Metadata-Version: 2.0
Name: WinPET
Version: 1.0.2
Summary: Windows Privilege Escalation Tester.
Home-page: https://github.com/hadi16/winpet
Author: Alex Hadi
Author-email: UNKNOWN
License: Apache License, Version 2.0
Platform: UNKNOWN
Classifier: License :: OSI Approved :: Apache Software License
Classifier: Operating System :: Microsoft :: Windows
Classifier: Programming Language :: Python :: 2.7
Classifier: Topic :: Security
Requires-Python: ==2.7.*
Requires-Dist: click
Requires-Dist: pywin32
